cv/Models.py
cv/TfDataset.py
cv/__init__.py
cv/classification/__init__.py
cv/classification/dataset/__init__.py
cv/classification/dataset/prepare.py
cv/module/__init__.py
cv/module/layers.py
cv/module/utils.py
cv/visualize/__init__.py
cv/yolov3/__init__.py
cv/yolov3/train.py
cv/yolov3/core/__init__.py
cv/yolov3/core/layers.py
cv/yolov3/core/models.py
cv/yolov3/core/utils.py
cv/yolov3/dataset/__init__.py
cv/yolov3/dataset/process_dataset.py
utils/__init__.py
utils/flag_utils.py
utils/gpu_setting.py
utils/image_processing.py
utils/keras_utils.py
utils/misc.py
utils/my_class.py
utils/os_path.py
utils/telegram_bot.py
utils/timeit.py
utils/video_processing.py
utils/label/VOCLabel.py
utils/label/__init__.py
utils/label/data_gen.py
utils/label/datapipe.py
mylib_maureen-2.4.9.dist-info/METADATA
mylib_maureen-2.4.9.dist-info/WHEEL
mylib_maureen-2.4.9.dist-info/top_level.txt
mylib_maureen-2.4.9.dist-info/RECORD
