Metadata-Version: 2.1
Name: mylib-maureen
Version: 2.4.9
Summary: my utils for cross-project use
Home-page: https://github.com/mohsu/mylib
Author: Maureen Hsu
License: UNKNOWN
Platform: UNKNOWN
Classifier: Programming Language :: Python :: 3
Classifier: License :: OSI Approved :: MIT License
Classifier: Operating System :: OS Independent
Requires-Python: >=3.7
Requires-Dist: pynvml
Requires-Dist: requests
Requires-Dist: loguru
Requires-Dist: numpy (==1.18.1)
Requires-Dist: matplotlib
Requires-Dist: configobj
